{
  "annotations": { "list": [] },
  "editable": true,
  "fiscalYearStartMonth": 0,
  "graphTooltip": 1,
  "id": null,
  "links": [],
  "panels": [
    {
      "datasource": { "type": "prometheus", "uid": "PBFA97CFB590B2093" },
      "fieldConfig": {
        "defaults": {
          "color": { "mode": "palette-classic" },
          "custom": {
            "axisCenteredZero": false,
            "axisLabel": "",
            "axisPlacement": "auto",
            "drawStyle": "line",
            "fillOpacity": 20,
            "gradientMode": "opacity",
            "lineInterpolation": "smooth",
            "lineWidth": 2,
            "pointSize": 5,
            "showPoints": "never",
            "spanNulls": false,
            "stacking": { "group": "A", "mode": "none" }
          },
          "thresholds": {
            "mode": "absolute",
            "steps": [
              { "color": "green", "value": null },
              { "color": "yellow", "value": 70 },
              { "color": "red", "value": 90 }
            ]
          },
          "unit": "percent"
        },
        "overrides": []
      },
      "gridPos": { "h": 8, "w": 12, "x": 0, "y": 0 },
      "id": 1,
      "options": {
        "legend": { "calcs": ["mean", "max"], "displayMode": "table", "placement": "bottom", "showLegend": true },
        "tooltip": { "mode": "multi", "sort": "desc" }
      },
      "targets": [
        { "expr": "autobot_cpu_usage_percent", "legendFormat": "CPU %", "refId": "A" }
      ],
      "title": "CPU Usage",
      "type": "timeseries"
    },
    {
      "datasource": { "type": "prometheus", "uid": "PBFA97CFB590B2093" },
      "fieldConfig": {
        "defaults": {
          "color": { "mode": "palette-classic" },
          "custom": {
            "axisCenteredZero": false,
            "axisLabel": "",
            "axisPlacement": "auto",
            "drawStyle": "line",
            "fillOpacity": 20,
            "gradientMode": "opacity",
            "lineInterpolation": "smooth",
            "lineWidth": 2,
            "pointSize": 5,
            "showPoints": "never",
            "spanNulls": false,
            "stacking": { "group": "A", "mode": "none" }
          },
          "thresholds": {
            "mode": "absolute",
            "steps": [
              { "color": "green", "value": null },
              { "color": "yellow", "value": 75 },
              { "color": "red", "value": 90 }
            ]
          },
          "unit": "percent"
        },
        "overrides": []
      },
      "gridPos": { "h": 8, "w": 12, "x": 12, "y": 0 },
      "id": 2,
      "options": {
        "legend": { "calcs": ["mean", "max"], "displayMode": "table", "placement": "bottom", "showLegend": true },
        "tooltip": { "mode": "multi", "sort": "desc" }
      },
      "targets": [
        { "expr": "autobot_memory_usage_percent", "legendFormat": "Memory %", "refId": "A" },
        { "expr": "autobot_memory_used_bytes / 1024 / 1024 / 1024", "legendFormat": "Used GB", "refId": "B" }
      ],
      "title": "Memory Usage",
      "type": "timeseries"
    },
    {
      "datasource": { "type": "prometheus", "uid": "PBFA97CFB590B2093" },
      "fieldConfig": {
        "defaults": {
          "color": { "mode": "thresholds" },
          "thresholds": {
            "mode": "absolute",
            "steps": [
              { "color": "green", "value": null },
              { "color": "yellow", "value": 80 },
              { "color": "red", "value": 95 }
            ]
          },
          "unit": "percent"
        },
        "overrides": []
      },
      "gridPos": { "h": 6, "w": 8, "x": 0, "y": 8 },
      "id": 3,
      "options": {
        "displayMode": "lcd",
        "minVizHeight": 10,
        "minVizWidth": 0,
        "orientation": "horizontal",
        "reduceOptions": { "calcs": ["lastNotNull"], "fields": "", "values": false },
        "showUnfilled": true,
        "valueMode": "color"
      },
      "targets": [
        { "expr": "autobot_disk_usage_percent", "legendFormat": "{{mount_point}}", "refId": "A" }
      ],
      "title": "Disk Usage by Mount Point",
      "type": "bargauge"
    },
    {
      "datasource": { "type": "prometheus", "uid": "PBFA97CFB590B2093" },
      "fieldConfig": {
        "defaults": {
          "color": { "mode": "palette-classic" },
          "custom": {
            "axisCenteredZero": false,
            "axisLabel": "",
            "axisPlacement": "auto",
            "drawStyle": "line",
            "fillOpacity": 10,
            "gradientMode": "none",
            "lineInterpolation": "smooth",
            "lineWidth": 2,
            "pointSize": 5,
            "showPoints": "never",
            "spanNulls": false,
            "stacking": { "group": "A", "mode": "none" }
          },
          "unit": "Bps"
        },
        "overrides": []
      },
      "gridPos": { "h": 6, "w": 8, "x": 8, "y": 8 },
      "id": 4,
      "options": {
        "legend": { "calcs": ["mean", "max"], "displayMode": "table", "placement": "bottom", "showLegend": true },
        "tooltip": { "mode": "multi", "sort": "desc" }
      },
      "targets": [
        { "expr": "rate(autobot_network_bytes_total{direction=\"in\"}[1m])", "legendFormat": "In", "refId": "A" },
        { "expr": "rate(autobot_network_bytes_total{direction=\"out\"}[1m])", "legendFormat": "Out", "refId": "B" }
      ],
      "title": "Network I/O",
      "type": "timeseries"
    },
    {
      "datasource": { "type": "prometheus", "uid": "PBFA97CFB590B2093" },
      "fieldConfig": {
        "defaults": {
          "color": { "mode": "thresholds" },
          "thresholds": {
            "mode": "absolute",
            "steps": [
              { "color": "blue", "value": null }
            ]
          }
        },
        "overrides": []
      },
      "gridPos": { "h": 6, "w": 4, "x": 16, "y": 8 },
      "id": 5,
      "options": {
        "colorMode": "value",
        "graphMode": "none",
        "justifyMode": "auto",
        "orientation": "auto",
        "reduceOptions": { "calcs": ["lastNotNull"], "fields": "", "values": false },
        "textMode": "auto"
      },
      "targets": [
        { "expr": "autobot_process_count", "legendFormat": "Processes", "refId": "A" }
      ],
      "title": "Process Count",
      "type": "stat"
    },
    {
      "datasource": { "type": "prometheus", "uid": "PBFA97CFB590B2093" },
      "fieldConfig": {
        "defaults": {
          "color": { "mode": "thresholds" },
          "thresholds": {
            "mode": "absolute",
            "steps": [
              { "color": "green", "value": null },
              { "color": "yellow", "value": 2 },
              { "color": "red", "value": 5 }
            ]
          }
        },
        "overrides": []
      },
      "gridPos": { "h": 6, "w": 4, "x": 20, "y": 8 },
      "id": 6,
      "options": {
        "colorMode": "value",
        "graphMode": "area",
        "justifyMode": "auto",
        "orientation": "auto",
        "reduceOptions": { "calcs": ["lastNotNull"], "fields": "", "values": false },
        "textMode": "auto"
      },
      "targets": [
        { "expr": "autobot_load_average_1m", "legendFormat": "1m", "refId": "A" }
      ],
      "title": "Load Average (1m)",
      "type": "stat"
    },
    {
      "datasource": { "type": "prometheus", "uid": "PBFA97CFB590B2093" },
      "fieldConfig": {
        "defaults": {
          "color": { "mode": "palette-classic" },
          "custom": {
            "axisCenteredZero": false,
            "axisLabel": "",
            "axisPlacement": "auto",
            "drawStyle": "line",
            "fillOpacity": 10,
            "gradientMode": "none",
            "lineInterpolation": "smooth",
            "lineWidth": 2,
            "pointSize": 5,
            "showPoints": "never",
            "spanNulls": false,
            "stacking": { "group": "A", "mode": "none" }
          }
        },
        "overrides": []
      },
      "gridPos": { "h": 8, "w": 24, "x": 0, "y": 14 },
      "id": 7,
      "options": {
        "legend": { "calcs": ["mean", "max"], "displayMode": "table", "placement": "bottom", "showLegend": true },
        "tooltip": { "mode": "multi", "sort": "desc" }
      },
      "targets": [
        { "expr": "autobot_load_average_1m", "legendFormat": "1m", "refId": "A" },
        { "expr": "autobot_load_average_5m", "legendFormat": "5m", "refId": "B" },
        { "expr": "autobot_load_average_15m", "legendFormat": "15m", "refId": "C" }
      ],
      "title": "Load Average",
      "type": "timeseries"
    }
  ],
  "refresh": "5s",
  "schemaVersion": 38,
  "tags": ["autobot", "system"],
  "templating": { "list": [] },
  "time": { "from": "now-1h", "to": "now" },
  "timepicker": {},
  "timezone": "browser",
  "title": "AutoBot System Metrics",
  "uid": "autobot-system",
  "version": 1,
  "weekStart": ""
}
